{
    "id": 5,
    "name": "Primary Auditory Cortex Network",
    "activeExperimentId": 1,
    "experiments": [
	    {
		  	id:1,      
		  	name: "Auditory Cortex NEURON simulation",
		  	status: "COMPLETED",
		  	description:"Network model of primary auditory cortex in rodents. David Beeman, University of Colorado, Boulder. Model developed in NeuroML. Simulation executed in NEURON. For more information see http://opensourcebrain.org/projects/acnet2.",
            "lastModified":"1436102517799",
		  	script: "/projects/AuditoryCortex/script.js",
		  	aspectConfigurations: [
		    {
		  		id:1,
		  		aspect: {
		            id: 1,
		            instancePath: "acnet2"
		        },
		        simulatorConfiguration: {
		          id: 1,
		          simulatorId: "neuronSimulator",
		          conversionServiceId: "lemsConversion",
		          timestep: 0.00001,
		          length: 0.3,
		          parameters: {target: "network_ACnet2"}
		        },
		        watchedVariables:[
			        {
			            id: 1,
			            instancePath: "acnet2.pyramidals_48[0].compartment_0.v"
			        },
			        			        {
			            id: 2,
			            instancePath: "acnet2.pyramidals_48[1].compartment_0.v"
			        },
			        {
			            id: 3,
			            instancePath: "acnet2.baskets_12[2].compartment_0.v"
			        }
		        ]
		  	}
		  	],
		  	simulationResults: [
		  	{
		  		id:1,
		  		format: "GEPPETTO_RECORDING",
		  		aspect: {
		            id: 1,
		            instancePath: "acnet2"
		        },
		        result: {
		          id: 1,
		          url: "/projects/AuditoryCortex/results.h5",
		          type: "RECORDING"
		        }
		  	},
		  	{
		  		id:2,
		  		format: "RAW",
		  		aspect: {
		            id: 1,
					instancePath: "acnet2"
		        },
		        result: {
		          id: 2,
		          url: "/projects/AuditoryCortex/rawRecording.zip",
		          type: "RECORDING"
		        }
		  	}]
	}
    ],
    "geppettoModel": {
        "id": 9,
        "url": "/projects/AuditoryCortex/GeppettoModel.xmi",
        "type": "GEPPETTO_PROJECT"
    }
}